datawhispers/__init__.py
datawhispers/advanced_prog.py
datawhispers/datavis.py
datawhsipers-0.1.dist-info/LICENSE
datawhsipers-0.1.dist-info/METADATA
datawhsipers-0.1.dist-info/WHEEL
datawhsipers-0.1.dist-info/top_level.txt
datawhsipers-0.1.dist-info/RECORD
